hyko_sdk_test/__init__.py
hyko_sdk_test/function.py
hyko_sdk_test/io.py
hyko_sdk_test/metadata.py
hyko_sdk_test/types.py
hyko_sdk_test/utils.py
hyko_sdk_test-0.4.18.dist-info/METADATA
hyko_sdk_test-0.4.18.dist-info/WHEEL
hyko_sdk_test-0.4.18.dist-info/RECORD
