Metadata-Version: 2.1
Name: hyko-sdk-test
Version: 0.4.18
Summary: Hyko's AI software development kit
Author: Ouassim Abdelmalek Ghribi
Author-email: oag@big-mama.io
Requires-Python: >=3.10,<4.0
Classifier: Programming Language :: Python :: 3
Classifier: Programming Language :: Python :: 3.10
Classifier: Programming Language :: Python :: 3.11
Requires-Dist: fastapi (>=0.105.0,<0.106.0)
Requires-Dist: h2 (>=4.1.0,<5.0.0)
Requires-Dist: httpx (>=0.26.0,<0.27.0)
Requires-Dist: numpy (>=1.26.2,<2.0.0)
Requires-Dist: pillow (>=10.1.0,<11.0.0)
Requires-Dist: pydantic (>=2.5.3,<3.0.0)
Requires-Dist: pymongo (>=4.6.1,<5.0.0)
Requires-Dist: soundfile (>=0.12.1,<0.13.0)
Requires-Dist: tqdm (>=4.66.1,<5.0.0)
